auto_docker_labels/__init__.py
auto_docker_labels/auto_docker_labels.py
auto_docker_labels/cli.py
auto_docker_labels-0.2.3.dist-info/AUTHORS.rst
auto_docker_labels-0.2.3.dist-info/LICENSE
auto_docker_labels-0.2.3.dist-info/METADATA
auto_docker_labels-0.2.3.dist-info/WHEEL
auto_docker_labels-0.2.3.dist-info/entry_points.txt
auto_docker_labels-0.2.3.dist-info/top_level.txt
auto_docker_labels-0.2.3.dist-info/RECORD
