Metadata-Version: 2.1
Name: auto_docker_labels
Version: 0.2.3
Summary: Automatically generate Docker Swarm mode node
Home-page: https://github.com/khulnasoft/auto_docker_labels
Author: Sebastian Ramirez
Author-email: khulnasoft@gmail.com
License: MIT license
Keywords: auto_docker_labels
Classifier: Development Status :: 2 - Pre-Alpha
Classifier: Intended Audience :: Developers
Classifier: License :: OSI Approved :: MIT License
Classifier: Natural Language :: English
Classifier: Programming Language :: Python :: 3
Classifier: Programming Language :: Python :: 3.4
Classifier: Programming Language :: Python :: 3.5
Classifier: Programming Language :: Python :: 3.6
License-File: LICENSE
License-File: AUTHORS.rst
Requires-Dist: Click >=6.0
Requires-Dist: docker
Requires-Dist: pyyaml
